lighthouz/__init__.py
lighthouz/app.py
lighthouz/benchmark.py
lighthouz/evaluation.py
lighthouz/schema.py
lighthouz-0.0.5.dist-info/METADATA
lighthouz-0.0.5.dist-info/WHEEL
lighthouz-0.0.5.dist-info/top_level.txt
lighthouz-0.0.5.dist-info/RECORD
